{
    "os": "Linux-5.4.0-172-generic-x86_64-with-glibc2.35",
    "python": "3.10.12",
    "heartbeatAt": "2024-07-15T23:55:44.173758",
    "startedAt": "2024-07-15T23:55:43.426936",
    "docker": null,
    "cuda": null,
    "args": [],
    "state": "running",
    "program": "<python with no main file>",
    "codePathLocal": null,
    "host": "d6fc84c44e5a",
    "username": "root",
    "executable": "/bin/python",
    "cpu_count": 48,
    "cpu_count_logical": 96,
    "cpu_freq": {
        "current": 2962.6374895833337,
        "min": 1200.0,
        "max": 3700.0
    },
    "cpu_freq_per_core": [
        {
            "current": 2168.694,
            "min": 1200.0,
            "max": 3700.0
        },
        {
            "current": 3047.159,
            "min": 1200.0,
            "max": 3700.0
        },
        {
            "current": 3276.493,
            "min": 1200.0,
            "max": 3700.0
        },
        {
            "current": 3280.787,
            "min": 1200.0,
            "max": 3700.0
        },
        {
            "current": 3043.021,
            "min": 1200.0,
            "max": 3700.0
        },
        {
            "current": 3287.295,
            "min": 1200.0,
            "max": 3700.0
        },
        {
            "current": 3079.312,
            "min": 1200.0,
            "max": 3700.0
        },
        {
            "current": 2903.641,
            "min": 1200.0,
            "max": 3700.0
        },
        {
            "current": 2904.303,
            "min": 1200.0,
            "max": 3700.0
        },
        {
            "current": 2905.906,
            "min": 1200.0,
            "max": 3700.0
        },
        {
            "current": 2996.927,
            "min": 1200.0,
            "max": 3700.0
        },
        {
            "current": 2910.803,
            "min": 1200.0,
            "max": 3700.0
        },
        {
            "current": 2897.983,
            "min": 1200.0,
            "max": 3700.0
        },
        {
            "current": 3152.301,
            "min": 1200.0,
            "max": 3700.0
        },
        {
            "current": 3128.694,
            "min": 1200.0,
            "max": 3700.0
        },
        {
            "current": 2816.654,
            "min": 1200.0,
            "max": 3700.0
        },
        {
            "current": 2906.653,
            "min": 1200.0,
            "max": 3700.0
        },
        {
            "current": 2979.013,
            "min": 1200.0,
            "max": 3700.0
        },
        {
            "current": 2897.57,
            "min": 1200.0,
            "max": 3700.0
        },
        {
            "current": 2898.961,
            "min": 1200.0,
            "max": 3700.0
        },
        {
            "current": 2475.901,
            "min": 1200.0,
            "max": 3700.0
        },
        {
            "current": 2473.28,
            "min": 1200.0,
            "max": 3700.0
        },
        {
            "current": 2479.15,
            "min": 1200.0,
            "max": 3700.0
        },
        {
            "current": 2486.484,
            "min": 1200.0,
            "max": 3700.0
        },
        {
            "current": 2882.316,
            "min": 1200.0,
            "max": 3700.0
        },
        {
            "current": 2890.31,
            "min": 1200.0,
            "max": 3700.0
        },
        {
            "current": 2958.371,
            "min": 1200.0,
            "max": 3700.0
        },
        {
            "current": 2897.017,
            "min": 1200.0,
            "max": 3700.0
        },
        {
            "current": 3385.627,
            "min": 1200.0,
            "max": 3700.0
        },
        {
            "current": 3487.023,
            "min": 1200.0,
            "max": 3700.0
        },
        {
            "current": 2885.507,
            "min": 1200.0,
            "max": 3700.0
        },
        {
            "current": 2891.064,
            "min": 1200.0,
            "max": 3700.0
        },
        {
            "current": 3247.33,
            "min": 1200.0,
            "max": 3700.0
        },
        {
            "current": 3374.382,
            "min": 1200.0,
            "max": 3700.0
        },
        {
            "current": 2985.743,
            "min": 1200.0,
            "max": 3700.0
        },
        {
            "current": 3485.932,
            "min": 1200.0,
            "max": 3700.0
        },
        {
            "current": 2970.606,
            "min": 1200.0,
            "max": 3700.0
        },
        {
            "current": 2808.407,
            "min": 1200.0,
            "max": 3700.0
        },
        {
            "current": 2804.703,
            "min": 1200.0,
            "max": 3700.0
        },
        {
            "current": 2899.709,
            "min": 1200.0,
            "max": 3700.0
        },
        {
            "current": 3395.229,
            "min": 1200.0,
            "max": 3700.0
        },
        {
            "current": 3127.446,
            "min": 1200.0,
            "max": 3700.0
        },
        {
            "current": 2890.997,
            "min": 1200.0,
            "max": 3700.0
        },
        {
            "current": 2900.564,
            "min": 1200.0,
            "max": 3700.0
        },
        {
            "current": 2904.398,
            "min": 1200.0,
            "max": 3700.0
        },
        {
            "current": 2907.053,
            "min": 1200.0,
            "max": 3700.0
        },
        {
            "current": 2923.267,
            "min": 1200.0,
            "max": 3700.0
        },
        {
            "current": 2919.335,
            "min": 1200.0,
            "max": 3700.0
        },
        {
            "current": 3347.442,
            "min": 1200.0,
            "max": 3700.0
        },
        {
            "current": 2955.856,
            "min": 1200.0,
            "max": 3700.0
        },
        {
            "current": 3117.817,
            "min": 1200.0,
            "max": 3700.0
        },
        {
            "current": 2955.064,
            "min": 1200.0,
            "max": 3700.0
        },
        {
            "current": 3259.573,
            "min": 1200.0,
            "max": 3700.0
        },
        {
            "current": 3401.477,
            "min": 1200.0,
            "max": 3700.0
        },
        {
            "current": 2896.428,
            "min": 1200.0,
            "max": 3700.0
        },
        {
            "current": 3044.392,
            "min": 1200.0,
            "max": 3700.0
        },
        {
            "current": 2900.1,
            "min": 1200.0,
            "max": 3700.0
        },
        {
            "current": 2900.482,
            "min": 1200.0,
            "max": 3700.0
        },
        {
            "current": 3066.933,
            "min": 1200.0,
            "max": 3700.0
        },
        {
            "current": 2909.905,
            "min": 1200.0,
            "max": 3700.0
        },
        {
            "current": 2891.465,
            "min": 1200.0,
            "max": 3700.0
        },
        {
            "current": 3399.349,
            "min": 1200.0,
            "max": 3700.0
        },
        {
            "current": 3302.816,
            "min": 1200.0,
            "max": 3700.0
        },
        {
            "current": 2900.809,
            "min": 1200.0,
            "max": 3700.0
        },
        {
            "current": 2903.507,
            "min": 1200.0,
            "max": 3700.0
        },
        {
            "current": 2948.36,
            "min": 1200.0,
            "max": 3700.0
        },
        {
            "current": 3233.627,
            "min": 1200.0,
            "max": 3700.0
        },
        {
            "current": 3234.751,
            "min": 1200.0,
            "max": 3700.0
        },
        {
            "current": 3194.157,
            "min": 1200.0,
            "max": 3700.0
        },
        {
            "current": 2538.777,
            "min": 1200.0,
            "max": 3700.0
        },
        {
            "current": 2555.297,
            "min": 1200.0,
            "max": 3700.0
        },
        {
            "current": 2550.538,
            "min": 1200.0,
            "max": 3700.0
        },
        {
            "current": 2882.831,
            "min": 1200.0,
            "max": 3700.0
        },
        {
            "current": 2888.992,
            "min": 1200.0,
            "max": 3700.0
        },
        {
            "current": 3222.803,
            "min": 1200.0,
            "max": 3700.0
        },
        {
            "current": 2899.676,
            "min": 1200.0,
            "max": 3700.0
        },
        {
            "current": 2967.526,
            "min": 1200.0,
            "max": 3700.0
        },
        {
            "current": 3400.518,
            "min": 1200.0,
            "max": 3700.0
        },
        {
            "current": 2893.804,
            "min": 1200.0,
            "max": 3700.0
        },
        {
            "current": 2897.641,
            "min": 1200.0,
            "max": 3700.0
        },
        {
            "current": 3364.378,
            "min": 1200.0,
            "max": 3700.0
        },
        {
            "current": 3134.257,
            "min": 1200.0,
            "max": 3700.0
        },
        {
            "current": 2909.919,
            "min": 1200.0,
            "max": 3700.0
        },
        {
            "current": 3430.703,
            "min": 1200.0,
            "max": 3700.0
        },
        {
            "current": 2990.382,
            "min": 1200.0,
            "max": 3700.0
        },
        {
            "current": 2990.685,
            "min": 1200.0,
            "max": 3700.0
        },
        {
            "current": 3000.664,
            "min": 1200.0,
            "max": 3700.0
        },
        {
            "current": 2904.272,
            "min": 1200.0,
            "max": 3700.0
        },
        {
            "current": 3427.417,
            "min": 1200.0,
            "max": 3700.0
        },
        {
            "current": 2850.06,
            "min": 1200.0,
            "max": 3700.0
        },
        {
            "current": 3073.039,
            "min": 1200.0,
            "max": 3700.0
        },
        {
            "current": 2897.578,
            "min": 1200.0,
            "max": 3700.0
        },
        {
            "current": 2896.599,
            "min": 1200.0,
            "max": 3700.0
        },
        {
            "current": 2906.813,
            "min": 1200.0,
            "max": 3700.0
        },
        {
            "current": 2922.747,
            "min": 1200.0,
            "max": 3700.0
        },
        {
            "current": 3099.724,
            "min": 1200.0,
            "max": 3700.0
        }
    ],
    "disk": {
        "/": {
            "total": 877.785945892334,
            "used": 733.4085731506348
        }
    },
    "gpu": "Tesla V100-SXM3-32GB",
    "gpu_count": 16,
    "gpu_devices": [
        {
            "name": "Tesla V100-SXM3-32GB",
            "memory_total": 34359738368
        },
        {
            "name": "Tesla V100-SXM3-32GB",
            "memory_total": 34359738368
        },
        {
            "name": "Tesla V100-SXM3-32GB",
            "memory_total": 34359738368
        },
        {
            "name": "Tesla V100-SXM3-32GB",
            "memory_total": 34359738368
        },
        {
            "name": "Tesla V100-SXM3-32GB",
            "memory_total": 34359738368
        },
        {
            "name": "Tesla V100-SXM3-32GB",
            "memory_total": 34359738368
        },
        {
            "name": "Tesla V100-SXM3-32GB",
            "memory_total": 34359738368
        },
        {
            "name": "Tesla V100-SXM3-32GB",
            "memory_total": 34359738368
        },
        {
            "name": "Tesla V100-SXM3-32GB",
            "memory_total": 34359738368
        },
        {
            "name": "Tesla V100-SXM3-32GB",
            "memory_total": 34359738368
        },
        {
            "name": "Tesla V100-SXM3-32GB",
            "memory_total": 34359738368
        },
        {
            "name": "Tesla V100-SXM3-32GB",
            "memory_total": 34359738368
        },
        {
            "name": "Tesla V100-SXM3-32GB",
            "memory_total": 34359738368
        },
        {
            "name": "Tesla V100-SXM3-32GB",
            "memory_total": 34359738368
        },
        {
            "name": "Tesla V100-SXM3-32GB",
            "memory_total": 34359738368
        },
        {
            "name": "Tesla V100-SXM3-32GB",
            "memory_total": 34359738368
        }
    ],
    "memory": {
        "total": 1510.5472717285156
    }
}
