{
    "os": "Linux-5.4.0-172-generic-x86_64-with-glibc2.35",
    "python": "3.10.12",
    "heartbeatAt": "2024-07-16T16:26:29.914526",
    "startedAt": "2024-07-16T16:26:29.163365",
    "docker": null,
    "cuda": null,
    "args": [],
    "state": "running",
    "program": "<python with no main file>",
    "codePathLocal": null,
    "host": "d6fc84c44e5a",
    "username": "root",
    "executable": "/bin/python",
    "cpu_count": 48,
    "cpu_count_logical": 96,
    "cpu_freq": {
        "current": 2163.2166354166675,
        "min": 1200.0,
        "max": 3700.0
    },
    "cpu_freq_per_core": [
        {
            "current": 1260.044,
            "min": 1200.0,
            "max": 3700.0
        },
        {
            "current": 1200.667,
            "min": 1200.0,
            "max": 3700.0
        },
        {
            "current": 1201.076,
            "min": 1200.0,
            "max": 3700.0
        },
        {
            "current": 1200.829,
            "min": 1200.0,
            "max": 3700.0
        },
        {
            "current": 1200.411,
            "min": 1200.0,
            "max": 3700.0
        },
        {
            "current": 1200.142,
            "min": 1200.0,
            "max": 3700.0
        },
        {
            "current": 1200.903,
            "min": 1200.0,
            "max": 3700.0
        },
        {
            "current": 1200.533,
            "min": 1200.0,
            "max": 3700.0
        },
        {
            "current": 1200.274,
            "min": 1200.0,
            "max": 3700.0
        },
        {
            "current": 1200.318,
            "min": 1200.0,
            "max": 3700.0
        },
        {
            "current": 1200.649,
            "min": 1200.0,
            "max": 3700.0
        },
        {
            "current": 1389.767,
            "min": 1200.0,
            "max": 3700.0
        },
        {
            "current": 1355.237,
            "min": 1200.0,
            "max": 3700.0
        },
        {
            "current": 1586.764,
            "min": 1200.0,
            "max": 3700.0
        },
        {
            "current": 1612.838,
            "min": 1200.0,
            "max": 3700.0
        },
        {
            "current": 2234.752,
            "min": 1200.0,
            "max": 3700.0
        },
        {
            "current": 2246.465,
            "min": 1200.0,
            "max": 3700.0
        },
        {
            "current": 1897.841,
            "min": 1200.0,
            "max": 3700.0
        },
        {
            "current": 1916.28,
            "min": 1200.0,
            "max": 3700.0
        },
        {
            "current": 1927.665,
            "min": 1200.0,
            "max": 3700.0
        },
        {
            "current": 1262.998,
            "min": 1200.0,
            "max": 3700.0
        },
        {
            "current": 1590.823,
            "min": 1200.0,
            "max": 3700.0
        },
        {
            "current": 1656.615,
            "min": 1200.0,
            "max": 3700.0
        },
        {
            "current": 1651.622,
            "min": 1200.0,
            "max": 3700.0
        },
        {
            "current": 2966.058,
            "min": 1200.0,
            "max": 3700.0
        },
        {
            "current": 2890.268,
            "min": 1200.0,
            "max": 3700.0
        },
        {
            "current": 3304.767,
            "min": 1200.0,
            "max": 3700.0
        },
        {
            "current": 2899.111,
            "min": 1200.0,
            "max": 3700.0
        },
        {
            "current": 3129.117,
            "min": 1200.0,
            "max": 3700.0
        },
        {
            "current": 2899.904,
            "min": 1200.0,
            "max": 3700.0
        },
        {
            "current": 2890.693,
            "min": 1200.0,
            "max": 3700.0
        },
        {
            "current": 2888.117,
            "min": 1200.0,
            "max": 3700.0
        },
        {
            "current": 3305.877,
            "min": 1200.0,
            "max": 3700.0
        },
        {
            "current": 3206.795,
            "min": 1200.0,
            "max": 3700.0
        },
        {
            "current": 2902.594,
            "min": 1200.0,
            "max": 3700.0
        },
        {
            "current": 2909.479,
            "min": 1200.0,
            "max": 3700.0
        },
        {
            "current": 2887.009,
            "min": 1200.0,
            "max": 3700.0
        },
        {
            "current": 2905.794,
            "min": 1200.0,
            "max": 3700.0
        },
        {
            "current": 2888.176,
            "min": 1200.0,
            "max": 3700.0
        },
        {
            "current": 3563.917,
            "min": 1200.0,
            "max": 3700.0
        },
        {
            "current": 2902.075,
            "min": 1200.0,
            "max": 3700.0
        },
        {
            "current": 2820.296,
            "min": 1200.0,
            "max": 3700.0
        },
        {
            "current": 2894.121,
            "min": 1200.0,
            "max": 3700.0
        },
        {
            "current": 3539.792,
            "min": 1200.0,
            "max": 3700.0
        },
        {
            "current": 2899.356,
            "min": 1200.0,
            "max": 3700.0
        },
        {
            "current": 3076.791,
            "min": 1200.0,
            "max": 3700.0
        },
        {
            "current": 2935.753,
            "min": 1200.0,
            "max": 3700.0
        },
        {
            "current": 2994.605,
            "min": 1200.0,
            "max": 3700.0
        },
        {
            "current": 1201.073,
            "min": 1200.0,
            "max": 3700.0
        },
        {
            "current": 1200.665,
            "min": 1200.0,
            "max": 3700.0
        },
        {
            "current": 1201.011,
            "min": 1200.0,
            "max": 3700.0
        },
        {
            "current": 1200.591,
            "min": 1200.0,
            "max": 3700.0
        },
        {
            "current": 1200.7,
            "min": 1200.0,
            "max": 3700.0
        },
        {
            "current": 1200.577,
            "min": 1200.0,
            "max": 3700.0
        },
        {
            "current": 1200.53,
            "min": 1200.0,
            "max": 3700.0
        },
        {
            "current": 1200.536,
            "min": 1200.0,
            "max": 3700.0
        },
        {
            "current": 1200.656,
            "min": 1200.0,
            "max": 3700.0
        },
        {
            "current": 1200.528,
            "min": 1200.0,
            "max": 3700.0
        },
        {
            "current": 1200.169,
            "min": 1200.0,
            "max": 3700.0
        },
        {
            "current": 1200.526,
            "min": 1200.0,
            "max": 3700.0
        },
        {
            "current": 1200.111,
            "min": 1200.0,
            "max": 3700.0
        },
        {
            "current": 1370.813,
            "min": 1200.0,
            "max": 3700.0
        },
        {
            "current": 1373.178,
            "min": 1200.0,
            "max": 3700.0
        },
        {
            "current": 1381.758,
            "min": 1200.0,
            "max": 3700.0
        },
        {
            "current": 1731.433,
            "min": 1200.0,
            "max": 3700.0
        },
        {
            "current": 1498.691,
            "min": 1200.0,
            "max": 3700.0
        },
        {
            "current": 1496.276,
            "min": 1200.0,
            "max": 3700.0
        },
        {
            "current": 2128.663,
            "min": 1200.0,
            "max": 3700.0
        },
        {
            "current": 1311.669,
            "min": 1200.0,
            "max": 3700.0
        },
        {
            "current": 1386.866,
            "min": 1200.0,
            "max": 3700.0
        },
        {
            "current": 1443.593,
            "min": 1200.0,
            "max": 3700.0
        },
        {
            "current": 2984.064,
            "min": 1200.0,
            "max": 3700.0
        },
        {
            "current": 3334.275,
            "min": 1200.0,
            "max": 3700.0
        },
        {
            "current": 2881.748,
            "min": 1200.0,
            "max": 3700.0
        },
        {
            "current": 2971.434,
            "min": 1200.0,
            "max": 3700.0
        },
        {
            "current": 2893.048,
            "min": 1200.0,
            "max": 3700.0
        },
        {
            "current": 2897.74,
            "min": 1200.0,
            "max": 3700.0
        },
        {
            "current": 2900.291,
            "min": 1200.0,
            "max": 3700.0
        },
        {
            "current": 2893.382,
            "min": 1200.0,
            "max": 3700.0
        },
        {
            "current": 2909.397,
            "min": 1200.0,
            "max": 3700.0
        },
        {
            "current": 2898.674,
            "min": 1200.0,
            "max": 3700.0
        },
        {
            "current": 2907.128,
            "min": 1200.0,
            "max": 3700.0
        },
        {
            "current": 2907.28,
            "min": 1200.0,
            "max": 3700.0
        },
        {
            "current": 2928.396,
            "min": 1200.0,
            "max": 3700.0
        },
        {
            "current": 2900.56,
            "min": 1200.0,
            "max": 3700.0
        },
        {
            "current": 2932.264,
            "min": 1200.0,
            "max": 3700.0
        },
        {
            "current": 2902.67,
            "min": 1200.0,
            "max": 3700.0
        },
        {
            "current": 3521.299,
            "min": 1200.0,
            "max": 3700.0
        },
        {
            "current": 2904.227,
            "min": 1200.0,
            "max": 3700.0
        },
        {
            "current": 2983.423,
            "min": 1200.0,
            "max": 3700.0
        },
        {
            "current": 2894.724,
            "min": 1200.0,
            "max": 3700.0
        },
        {
            "current": 3229.905,
            "min": 1200.0,
            "max": 3700.0
        },
        {
            "current": 2903.423,
            "min": 1200.0,
            "max": 3700.0
        },
        {
            "current": 2796.361,
            "min": 1200.0,
            "max": 3700.0
        },
        {
            "current": 2937.636,
            "min": 1200.0,
            "max": 3700.0
        },
        {
            "current": 2971.224,
            "min": 1200.0,
            "max": 3700.0
        }
    ],
    "disk": {
        "/": {
            "total": 877.785945892334,
            "used": 733.1447257995605
        }
    },
    "gpu": "Tesla V100-SXM3-32GB",
    "gpu_count": 16,
    "gpu_devices": [
        {
            "name": "Tesla V100-SXM3-32GB",
            "memory_total": 34359738368
        },
        {
            "name": "Tesla V100-SXM3-32GB",
            "memory_total": 34359738368
        },
        {
            "name": "Tesla V100-SXM3-32GB",
            "memory_total": 34359738368
        },
        {
            "name": "Tesla V100-SXM3-32GB",
            "memory_total": 34359738368
        },
        {
            "name": "Tesla V100-SXM3-32GB",
            "memory_total": 34359738368
        },
        {
            "name": "Tesla V100-SXM3-32GB",
            "memory_total": 34359738368
        },
        {
            "name": "Tesla V100-SXM3-32GB",
            "memory_total": 34359738368
        },
        {
            "name": "Tesla V100-SXM3-32GB",
            "memory_total": 34359738368
        },
        {
            "name": "Tesla V100-SXM3-32GB",
            "memory_total": 34359738368
        },
        {
            "name": "Tesla V100-SXM3-32GB",
            "memory_total": 34359738368
        },
        {
            "name": "Tesla V100-SXM3-32GB",
            "memory_total": 34359738368
        },
        {
            "name": "Tesla V100-SXM3-32GB",
            "memory_total": 34359738368
        },
        {
            "name": "Tesla V100-SXM3-32GB",
            "memory_total": 34359738368
        },
        {
            "name": "Tesla V100-SXM3-32GB",
            "memory_total": 34359738368
        },
        {
            "name": "Tesla V100-SXM3-32GB",
            "memory_total": 34359738368
        },
        {
            "name": "Tesla V100-SXM3-32GB",
            "memory_total": 34359738368
        }
    ],
    "memory": {
        "total": 1510.5472717285156
    }
}
